supersurf/__init__.py
supersurf-0.0.1.dist-info/METADATA
supersurf-0.0.1.dist-info/WHEEL
supersurf-0.0.1.dist-info/RECORD
