Metadata-Version: 2.3
Name: supersurf
Version: 0.0.1
Summary: supersurf
License: MIT
Author: Your Name
Author-email: you@example.com
Requires-Python: >=3.13
Classifier: License :: OSI Approved :: MIT License
Classifier: Programming Language :: Python :: 3
Classifier: Programming Language :: Python :: 3.13
